{
  "text": "ScrapRunner",
  "link": "{{appSetting-ExplorerHostUrl}}/view/#default/explorer/View",
  "items": [
    {
      "text": "SR Tables",
      "items": [
        {
          "text": "CodeTable",
          "link": "{{appSetting-ExplorerHostUrl}}/view/#default/scraprunner/CodeTable"
        },
        {
          "text": "CodeTableHdr",
          "link": "{{appSetting-ExplorerHostUrl}}/view/#default/scraprunner/CodeTableHdr"
        },
        {
          "text": "CommodityMaster",
          "link": "{{appSetting-ExplorerHostUrl}}/view/#default/scraprunner/CommodityMaster"
        },
        {
          "text": "Container",
          "items": [
            {
              "text": "ContainerChange",
              "link": "{{appSetting-ExplorerHostUrl}}/view/#default/scraprunner/ContainerChange"
            },
            {
              "text": "ContainerMaster",
              "link": "{{appSetting-ExplorerHostUrl}}/view/#default/scraprunner/ContainerMaster"
            }
          ]
        },
        {
          "text": "Customer",
          "items": [
            {
              "text": "CustomerCommodity",
              "link": "{{appSetting-ExplorerHostUrl}}/view/#default/scraprunner/CustomerCommodity"
            },
            {
              "text": "CustomerLocation",
              "link": "{{appSetting-ExplorerHostUrl}}/view/#default/scraprunner/CustomerLocation"
            },
            {
              "text": "CustomerMaster",
              "link": "{{appSetting-ExplorerHostUrl}}/view/#default/scraprunner/CustomerMaster"
            }
          ]
        },
        {
          "text": "Driver",
          "items": [
            {
              "text": "DriverDelay",
              "link": "{{appSetting-ExplorerHostUrl}}/view/#default/scraprunner/DriverDelay"
            },
            {
              "text": "DriverHistory",
              "link": "{{appSetting-ExplorerHostUrl}}/view/#default/scraprunner/DriverHistory"
            },
            {
              "text": "DriverStatus",
              "link": "{{appSetting-ExplorerHostUrl}}/view/#default/scraprunner/DriverStatus"
            }
          ]
        },
        {
          "text": "EmployeeMaster",
          "link": "{{appSetting-ExplorerHostUrl}}/view/#default/scraprunner/EmployeeMaster"
        },
        {
          "text": "Logs",
          "items": [
            {
              "text": "ErrorLog",
              "link": "{{appSetting-ExplorerHostUrl}}/view/#default/scraprunner/ErrorLog"
            },
            {
              "text": "EventLog",
              "link": "{{appSetting-ExplorerHostUrl}}/view/#default/scraprunner/EventLog"
            }
          ]
        },
        {
          "text": "Power",
          "items": [
            {
              "text": "PowerHistory",
              "link": "{{appSetting-ExplorerHostUrl}}/view/#default/scraprunner/PowerHistory"
            },
            {
              "text": "PowerMaster",
              "link": "{{appSetting-ExplorerHostUrl}}/view/#default/scraprunner/PowerMaster"
            }
          ]
        },
        {
          "text": "Preferences",
          "link": "{{appSetting-ExplorerHostUrl}}/view/#default/scraprunner/Preference"
        },
        {
          "text": "RegionMaster",
          "link": "{{appSetting-ExplorerHostUrl}}/view/#default/scraprunner/RegionMaster"
        },
        {
          "text": "Terminal",
          "items": [
            {
              "text": "TerminalChange",
              "link": "{{appSetting-ExplorerHostUrl}}/view/#default/scraprunner/TerminalChange"
            },
            {
              "text": "TerminalMaster",
              "link": "{{appSetting-ExplorerHostUrl}}/view/#default/scraprunner/TerminalMaster"
            }
          ]
        },
        {
          "text": "Trip",
          "items": [
            {
              "text": "Trip",
              "link": "{{appSetting-ExplorerHostUrl}}/view/#default/scraprunner/Trip"
            },
            {
              "text": "TripReferenceNumber",
              "link": "{{appSetting-ExplorerHostUrl}}/view/#default/scraprunner/TripReferenceNumber"
            },
            {
              "text": "TripSegment",
              "link": "{{appSetting-ExplorerHostUrl}}/view/#default/scraprunner/TripSegment"
            },
            {
              "text": "TripSegmentMileage",
              "link": "{{appSetting-ExplorerHostUrl}}/view/#default/scraprunner/TripSegmentMileage"
            },
            {
              "text": "TripTypeBasic",
              "link": "{{appSetting-ExplorerHostUrl}}/view/#default/scraprunner/TripTypeBasic"
            }
          ]
        }
      ]
    }
  ]
}
